azure/mgmt/desktopvirtualization/__init__.py
azure/mgmt/desktopvirtualization/_configuration.py
azure/mgmt/desktopvirtualization/_desktop_virtualization_mgmt_client.py
azure/mgmt/desktopvirtualization/_patch.py
azure/mgmt/desktopvirtualization/_serialization.py
azure/mgmt/desktopvirtualization/_version.py
azure/mgmt/desktopvirtualization/py.typed
azure/mgmt/desktopvirtualization/aio/__init__.py
azure/mgmt/desktopvirtualization/aio/_configuration.py
azure/mgmt/desktopvirtualization/aio/_desktop_virtualization_mgmt_client.py
azure/mgmt/desktopvirtualization/aio/_patch.py
azure/mgmt/desktopvirtualization/aio/operations/__init__.py
azure/mgmt/desktopvirtualization/aio/operations/_app_attach_package_info_operations.py
azure/mgmt/desktopvirtualization/aio/operations/_app_attach_package_operations.py
azure/mgmt/desktopvirtualization/aio/operations/_application_groups_operations.py
azure/mgmt/desktopvirtualization/aio/operations/_applications_operations.py
azure/mgmt/desktopvirtualization/aio/operations/_desktops_operations.py
azure/mgmt/desktopvirtualization/aio/operations/_host_pools_operations.py
azure/mgmt/desktopvirtualization/aio/operations/_msix_images_operations.py
azure/mgmt/desktopvirtualization/aio/operations/_msix_packages_operations.py
azure/mgmt/desktopvirtualization/aio/operations/_operations.py
azure/mgmt/desktopvirtualization/aio/operations/_patch.py
azure/mgmt/desktopvirtualization/aio/operations/_private_endpoint_connections_operations.py
azure/mgmt/desktopvirtualization/aio/operations/_private_link_resources_operations.py
azure/mgmt/desktopvirtualization/aio/operations/_scaling_plan_personal_schedules_operations.py
azure/mgmt/desktopvirtualization/aio/operations/_scaling_plan_pooled_schedules_operations.py
azure/mgmt/desktopvirtualization/aio/operations/_scaling_plans_operations.py
azure/mgmt/desktopvirtualization/aio/operations/_session_hosts_operations.py
azure/mgmt/desktopvirtualization/aio/operations/_start_menu_items_operations.py
azure_mgmt_desktopvirtualization-2.0.0.dist-info/LICENSE
azure_mgmt_desktopvirtualization-2.0.0.dist-info/LICENSE.txt
azure_mgmt_desktopvirtualization-2.0.0.dist-info/METADATA
azure_mgmt_desktopvirtualization-2.0.0.dist-info/WHEEL
azure_mgmt_desktopvirtualization-2.0.0.dist-info/top_level.txt
azure_mgmt_desktopvirtualization-2.0.0.dist-info/RECORD
